Workbook

Sheet 松山紹介_補綴価格表
A1: 松山翼様ご紹介プラン｜補綴（セラミック治療）価格表 ※医院内部用・粗利つき
A2: 単位：円 ／ 定価＝患者請求(税込) ／ 技工料＝技工所への支払(税別) ／ 利益＝紹介価格−技工料 ／ 本数に関わらず一律20%OFF（＝当院の値引き下限を最初から適用）
A3: 元データ：自費補綴 粗利表（本数によるまとめ割引 最大20%OFF・下限）。20%OFFは新設の値引きではなく、既存ルールの下限価格をそのまま紹介特典にしたもの。
A5: 【設定値】ここを変えると下表がすべて再計算されます（青字＝入力セル）
A6: 松山翼様ご紹介の割引率（補綴） | C6: 0.2 | D6: ← 当院の値引き下限。これ以上は下げない
A7: ［比較用］紹介なし・単品1〜2本のときに通常出せる割引率 | C7: 0.1 | D7: ← I列（実質の追加負担）の計算基準
A9: 品目 | B9: 定価(税込) | C9: 技工料 | D9: 松山紹介価格 (20%OFF) | E9: 患者の割引額 | F9: 紹介時の利益 | G9: 紹介時の 粗利率 | H9: ［比較］通常単品時 価格(10%OFF) | I9: 通常比の 医院追加負担 | J9: 備考
A10: ■ 臼歯部（YOZE｜技工料 一律 10,136円＝10,000＋ベースアップ評価料136）
A11: フルジルコニアクラウン | B11: 99000 | C11: 10136 | D11: =ROUND(B11*(1-$C$6),0) -> 79200 | E11: =B11-D11 -> 19800 | F11: =D11-C11 -> 69064 | G11: =F11/D11 -> 0.8720202 | H11: =ROUND(B11*(1-$C$7),0) -> 89100 | I11: =H11-D11 -> 9900 | J11: iTero送信のCAD製作なら技工料 −1,000円（利益さらに+1,000）
A12: e-maxクラウン | B12: 99000 | C12: 10136 | D12: =ROUND(B12*(1-$C$6),0) -> 79200 | E12: =B12-D12 -> 19800 | F12: =D12-C12 -> 69064 | G12: =F12/D12 -> 0.8720202 | H12: =ROUND(B12*(1-$C$7),0) -> 89100 | I12: =H12-D12 -> 9900
A13: フルジルコニアインレー | B13: 55000 | C13: 10136 | D13: =ROUND(B13*(1-$C$6),0) -> 44000 | E13: =B13-D13 -> 11000 | F13: =D13-C13 -> 33864 | G13: =F13/D13 -> 0.76963636 | H13: =ROUND(B13*(1-$C$7),0) -> 49500 | I13: =H13-D13 -> 5500
A14: e-maxインレー | B14: 55000 | C14: 10136 | D14: =ROUND(B14*(1-$C$6),0) -> 44000 | E14: =B14-D14 -> 11000 | F14: =D14-C14 -> 33864 | G14: =F14/D14 -> 0.76963636 | H14: =ROUND(B14*(1-$C$7),0) -> 49500 | I14: =H14-D14 -> 5500
A15: ■ 前歯部（ティーラボ｜レイヤリング27,000／単色ステイン19,000／ベニア16,000）
A16: ジルコニアセラミック S級 | B16: 143000 | C16: 27000 | D16: =ROUND(B16*(1-$C$6),0) -> 114400 | E16: =B16-D16 -> 28600 | F16: =D16-C16 -> 87400 | G16: =F16/D16 -> 0.76398601 | H16: =ROUND(B16*(1-$C$7),0) -> 128700 | I16: =H16-D16 -> 14300 | J16: レイヤリング（盛り・グラデーション）
A17: ジルコニアセラミック ノーマル | B17: 110000 | C17: 19000 | D17: =ROUND(B17*(1-$C$6),0) -> 88000 | E17: =B17-D17 -> 22000 | F17: =D17-C17 -> 69000 | G17: =F17/D17 -> 0.78409091 | H17: =ROUND(B17*(1-$C$7),0) -> 99000 | I17: =H17-D17 -> 11000 | J17: 単色ステイン
A18: ラミネートベニア | B18: 110000 | C18: 16000 | D18: =ROUND(B18*(1-$C$6),0) -> 88000 | E18: =B18-D18 -> 22000 | F18: =D18-C18 -> 72000 | G18: =F18/D18 -> 0.81818182 | H18: =ROUND(B18*(1-$C$7),0) -> 99000 | I18: =H18-D18 -> 11000 | J18: Zrベニア／e.maxベニア
A19: スーパーエナメル | B19: 99000 | C19: 27000 | D19: =ROUND(B19*(1-$C$6),0) -> 79200 | E19: =B19-D19 -> 19800 | F19: =D19-C19 -> 52200 | G19: =F19/D19 -> 0.65909091 | H19: =ROUND(B19*(1-$C$7),0) -> 89100 | I19: =H19-D19 -> 9900 | J19: レイヤリング。20%OFF時の粗利率が全品目で最低。連冠時は特に注意
A20: e-maxクラウン（前歯） | B20: 99000 | C20: 19000 | D20: =ROUND(B20*(1-$C$6),0) -> 79200 | E20: =B20-D20 -> 19800 | F20: =D20-C20 -> 60200 | G20: =F20/D20 -> 0.76010101 | H20: =ROUND(B20*(1-$C$7),0) -> 89100 | I20: =H20-D20 -> 9900 | J20: 単色
A22: この価格表の読み方
A23: ◆ D列＝松山翼様ご紹介の方に提示する価格。1本からこの価格で、本数による条件なし。
A24: ◆ I列＝この制度の「本当のコスト」。紹介がなくても単品で10%OFFは出しているので、医院が新たに負担するのは定価の10%分だけ。
A25: ◆ 20%OFFでも粗利率は65.9〜87.2%を確保。原価割れは起きない（元データの下限ルールと同じ）。
A26: ◆ 連冠（ブリッジ状に連なる前歯）のレイヤリングは技工料が1歯につき+2,000円。スーパーエナメル6本連冠＝技工29,000/歯 → 20%OFF時の利益50,200円・粗利率63.4%まで下がる。
A27: ◆ ハイブリッドセラミッククラウンは扱い無しのため本表に無し。ジルコニア単色ステイン無し（今後12,000円ほどで対応予定）も未確定のため未掲載。
A29: 前提（元データと同じ）
A30: ◆ 利益＝紹介価格(税込)−技工料(税別)の簡易計算。消費税の納税分・材料費・チェアタイムは考慮していない。
A31: ◆ 実際の手取りは、上表の利益から消費税納税分と院内コストを引いた額になる。

Sheet 松山紹介_矯正価格表
A1: 松山翼様ご紹介プラン｜矯正（インビザライン）価格表 ※医院内部用・粗利つき
A2: 単位：円 ／ 矯正は【①矯正治療費】と【②矯正検査診断料】の別建て請求。紹介特典は②のみ無料にするもので、①のパッケージ価格は1円も下げない。
A3: 根拠：元データ 矯正_値引き価格表 A25「値引きを求められた場合は、価格を下げるより矯正検査診断料44,000円（原価ゼロ）を無料にするほうが医院の負担が小さい」
A5: 【設定値】（青字＝入力セル）
A6: 無料にする矯正検査診断料（税込・アラインへの支払いなし＝丸ごと利益） | E6: 44000
A7: ［比較用］どうしても値引きする場合の下限割引率 | E7: 0.1
A9: 品目 | B9: ①矯正治療費 (税込・据え置き) | C9: パッケージ 22%OFF後 | D9: 手数料 (割引なし) | E9: ビベラ1set (割引なし) | F9: 原価合計 | G9: 通常時の請求額 ①+② | H9: 松山紹介の請求額 ①のみ | I9: ②矯正検査診断料 →無料にする額 | J9: 請求総額に対する 実質割引率 | K9: 紹介時の利益 | L9: 紹介時の 粗利率 | M9: ［比較］治療費を10%OFF にした場合の値引額
A10: ■ 大人（インビザライン） ※アライン価格は税別・22%OFF適用
A11: インビザラインフル（無制限）｜コンプリ オプション1 | B11: 880000 | C11: 232440 | D11: 3400 | E11: 10800 | F11: =C11+D11+E11 -> 246640 | G11: =B11+$E$6 -> 924000 | H11: =B11 -> 880000 | I11: =G11-H11 -> 44000 | J11: =I11/G11 -> 0.047619048 | K11: =H11-F11 -> 633360 | L11: =K11/H11 -> 0.71972727 | M11: =ROUND(B11*$E$7,0) -> 88000
A12: インビザラインフル（無制限）｜コンプリ オプション2 | B12: 880000 | C12: 195000 | D12: 3400 | E12: 10800 | F12: =C12+D12+E12 -> 209200 | G12: =B12+$E$6 -> 924000 | H12: =B12 -> 880000 | I12: =G12-H12 -> 44000 | J12: =I12/G12 -> 0.047619048 | K12: =H12-F12 -> 670800 | L12: =K12/H12 -> 0.76227273 | M12: =ROUND(B12*$E$7,0) -> 88000
A13: インビザラインモデレート（26枚）両顎 | B13: 547800 | C13: 156000 | D13: 3400 | E13: 10800 | F13: =C13+D13+E13 -> 170200 | G13: =B13+$E$6 -> 591800 | H13: =B13 -> 547800 | I13: =G13-H13 -> 44000 | J13: =I13/G13 -> 0.074349442 | K13: =H13-F13 -> 377600 | L13: =K13/H13 -> 0.68930267 | M13: =ROUND(B13*$E$7,0) -> 54780
A14: インビザラインモデレート 上下別（片顎） | B14: 497800 | C14: 117000 | D14: 3400 | E14: 8000 | F14: =C14+D14+E14 -> 128400 | G14: =B14+$E$6 -> 541800 | H14: =B14 -> 497800 | I14: =G14-H14 -> 44000 | J14: =I14/G14 -> 0.081210779 | K14: =H14-F14 -> 369400 | L14: =K14/H14 -> 0.74206509 | M14: =ROUND(B14*$E$7,0) -> 49780
A15: インビザラインライト（14枚）両顎 | B15: 437800 | C15: 129480 | D15: 3400 | E15: 10800 | F15: =C15+D15+E15 -> 143680 | G15: =B15+$E$6 -> 481800 | H15: =B15 -> 437800 | I15: =G15-H15 -> 44000 | J15: =I15/G15 -> 0.091324201 | K15: =H15-F15 -> 294120 | L15: =K15/H15 -> 0.67181361 | M15: =ROUND(B15*$E$7,0) -> 43780
A16: インビザラインライト 上下別（片顎） | B16: 393800 | C16: 96720 | D16: 3400 | E16: 8000 | F16: =C16+D16+E16 -> 108120 | G16: =B16+$E$6 -> 437800 | H16: =B16 -> 393800 | I16: =G16-H16 -> 44000 | J16: =I16/G16 -> 0.10050251 | K16: =H16-F16 -> 285680 | L16: =K16/H16 -> 0.72544439 | M16: =ROUND(B16*$E$7,0) -> 39380
A17: インビザラインエクスプレス（7枚）両顎 | B17: 327800 | C17: 100000 | D17: 3400 | E17: 10800 | F17: =C17+D17+E17 -> 114200 | G17: =B17+$E$6 -> 371800 | H17: =B17 -> 327800 | I17: =G17-H17 -> 44000 | J17: =I17/G17 -> 0.1183432 | K17: =H17-F17 -> 213600 | L17: =K17/H17 -> 0.65161684 | M17: =ROUND(B17*$E$7,0) -> 32780
A18: インビザラインエクスプレス 上下別（片顎） | B18: 298000 | C18: 78000 | D18: 3400 | E18: 8000 | F18: =C18+D18+E18 -> 89400 | G18: =B18+$E$6 -> 342000 | H18: =B18 -> 298000 | I18: =G18-H18 -> 44000 | J18: =I18/G18 -> 0.12865497 | K18: =H18-F18 -> 208600 | L18: =K18/H18 -> 0.7 | M18: =ROUND(B18*$E$7,0) -> 29800
A19: ■ 小児一期（インビザライン・ファースト）
A20: 小児一期｜ファースト オプション1（12か月） | B20: 550000 | C20: 137280 | D20: 3400 | E20: 10800 | F20: =C20+D20+E20 -> 151480 | G20: =B20+$E$6 -> 594000 | H20: =B20 -> 550000 | I20: =G20-H20 -> 44000 | J20: =I20/G20 -> 0.074074074 | K20: =H20-F20 -> 398520 | L20: =K20/H20 -> 0.72458182 | M20: =ROUND(B20*$E$7,0) -> 55000
A21: 小児一期｜ファースト オプション2（18か月）★推奨 | B21: 550000 | C21: 148200 | D21: 3400 | E21: 10800 | F21: =C21+D21+E21 -> 162400 | G21: =B21+$E$6 -> 594000 | H21: =B21 -> 550000 | I21: =G21-H21 -> 44000 | J21: =I21/G21 -> 0.074074074 | K21: =H21-F21 -> 387600 | L21: =K21/H21 -> 0.70472727 | M21: =ROUND(B21*$E$7,0) -> 55000
A22: 小児一期｜ファースト オプション3（24か月） | B22: 550000 | C22: 175500 | D22: 3400 | E22: 10800 | F22: =C22+D22+E22 -> 189700 | G22: =B22+$E$6 -> 594000 | H22: =B22 -> 550000 | I22: =G22-H22 -> 44000 | J22: =I22/G22 -> 0.074074074 | K22: =H22-F22 -> 360300 | L22: =K22/H22 -> 0.65509091 | M22: =ROUND(B22*$E$7,0) -> 55000
A23: ■ 小児二期
A24: 小児二期治療（フェーズ2） | B24: 440000 | C24: 144300 | D24: 3400 | E24: 10800 | F24: =C24+D24+E24 -> 158500 | G24: =B24+$E$6 -> 484000 | H24: =B24 -> 440000 | I24: =G24-H24 -> 44000 | J24: =I24/G24 -> 0.090909091 | K24: =H24-F24 -> 281500 | L24: =K24/H24 -> 0.63977273 | M24: =ROUND(B24*$E$7,0) -> 44000
A26: なぜ矯正は値引かず「検査診断料 44,000円 無料」にするのか
A27: ◆ 矯正の粗利率は定価でも64〜76%と低く、補綴のように20%も下げる余地がない。パッケージ価格を下げると原価率が一気に悪化する。
A28: ◆ 検査診断料44,000円はアラインへの支払いがゼロ＝丸ごと利益。無料にしても医院の持ち出しは一切発生せず、減るのは「もらえたはずの44,000円」だけ。
A29: ◆ M列（10%OFFの値引額）と I列（44,000円）を比べると、モデレート以上の高額パッケージでは検査診断料無料のほうが医院の負担が小さい。
A30: ◆【要注意】ライト両顎(43,780)・ライト片顎(39,380)・エクスプレス両顎(32,780)・エクスプレス片顎(29,800)は、10%OFFのほうが44,000円より安く済む（フェーズ2は44,000円で同額）。
A31: ただし表を2本立てにすると現場が混乱し「じゃあ10%OFFで」と言われる口実にもなるため、全パッケージ一律「検査診断料無料」で統一する。差額は最大14,200円（エクスプレス片顎）。
A33: 運用上の注意（元データより引き継ぎ）
A34: ◆ 矯正の請求は【①矯正治療費】と【②矯正検査診断料 44,000円】の別建て。②はアラインへの支払いが無いので原価ゼロ＝丸ごと利益。
A35: ◆ 原価合計＝パッケージ(22%OFF後)＋手数料3,400（初回アライナー＋ビベラの2回分）＋ビベラ1セット（定価・割引対象外）。②に対応する原価は無い。
A36: ◆ 追加アライナーが出るたびに手数料+1,700円、コンプリ オプション2・モデレート・ライト・フェーズ2は追加1回ごとに本体費用も発生する（元データ参照）。
A37: ◆ エクスプレスはアラインの割引が一切効かない（片顎78,000／両顎100,000が丸ごと請求）。粗利率が最も低いので、紹介プランでも値引きはしない。
A38: ◆ iTero送信の症例はキャンセル料0円（PVS印象は30,000円）。松山翼様紹介の症例は必ずiTeroで提出する運用にすると、キャンセル時の損失をゼロにできる。
A39: ◆ 松山翼様から矯正の値引きを強く求められた場合の最終ラインはM列（10%OFF）。ただし院長判断とし、価格表には載せない。

Sheet 損益分岐シミュレーション
A1: 従来の「月額紹介料」と、新方式「紹介の方への値引き」の損益比較
A2: この制度の最大のメリットは、紹介料が固定費から変動費に変わること。紹介がゼロの月の医院負担は、従来＝月額まるごと／新方式＝0円。
A3: 単位：円。補綴の「通常割引率」は既存の本数ルール（1〜5本10%／6〜9本15%／10本以上20%）を自動適用。矯正は原則値引きなしのため通常割引率0%。
A5: 【設定値】従来松山翼様に毎月お支払いしていた紹介料の実額を入れてください（青字＝入力セル）
A6: 従来の月額紹介料（実額に置き換えてください） | D6: 50000 | E6: 円／月 ★仮の数値です。必ず実額に修正してください
A7: 従来方式の年間負担 | D7: =D6*12 -> 600000 | E7: 円／年（紹介人数がゼロでも発生）
A9: 想定ケース | B9: 本数／件数 | C9: 単価(定価) | D9: 定価合計 | E9: 通常の 割引率 | F9: 紹介がなくても 出していた価格 | G9: 松山紹介価格 | H9: 患者メリット (定価との差) | I9: 医院の実質負担 (通常価格との差) | J9: 紹介時の医院の利益 | K9: 紹介時の 粗利率
A10: ■ 補綴（セラミック治療）｜松山紹介＝本数に関わらず一律20%OFF
A11: 臼歯 フルジルコニアクラウン 1本 | B11: 1 | C11: =松山紹介_補綴価格表!B11 -> 99000 | D11: =B11*C11 -> 99000 | E11: =IF(B11<=5,0.1,IF(B11<=9,0.15,0.2)) -> 0.1 | F11: =ROUND(C11*(1-E11),0)*B11 -> 89100 | G11: =松山紹介_補綴価格表!D11*B11 -> 79200 | H11: =D11-G11 -> 19800 | I11: =F11-G11 -> 9900 | J11: =松山紹介_補綴価格表!F11*B11 -> 69064 | K11: =J11/G11 -> 0.8720202
A12: 臼歯 フルジルコニアクラウン 3本 | B12: 3 | C12: =松山紹介_補綴価格表!B11 -> 99000 | D12: =B12*C12 -> 297000 | E12: =IF(B12<=5,0.1,IF(B12<=9,0.15,0.2)) -> 0.1 | F12: =ROUND(C12*(1-E12),0)*B12 -> 267300 | G12: =松山紹介_補綴価格表!D11*B12 -> 237600 | H12: =D12-G12 -> 59400 | I12: =F12-G12 -> 29700 | J12: =松山紹介_補綴価格表!F11*B12 -> 207192 | K12: =J12/G12 -> 0.8720202
A13: 臼歯 フルジルコニアインレー 2本 | B13: 2 | C13: =松山紹介_補綴価格表!B13 -> 55000 | D13: =B13*C13 -> 110000 | E13: =IF(B13<=5,0.1,IF(B13<=9,0.15,0.2)) -> 0.1 | F13: =ROUND(C13*(1-E13),0)*B13 -> 99000 | G13: =松山紹介_補綴価格表!D13*B13 -> 88000 | H13: =D13-G13 -> 22000 | I13: =F13-G13 -> 11000 | J13: =松山紹介_補綴価格表!F13*B13 -> 67728 | K13: =J13/G13 -> 0.76963636
A14: 前歯 ジルコニアセラミック S級 4本 | B14: 4 | C14: =松山紹介_補綴価格表!B16 -> 143000 | D14: =B14*C14 -> 572000 | E14: =IF(B14<=5,0.1,IF(B14<=9,0.15,0.2)) -> 0.1 | F14: =ROUND(C14*(1-E14),0)*B14 -> 514800 | G14: =松山紹介_補綴価格表!D16*B14 -> 457600 | H14: =D14-G14 -> 114400 | I14: =F14-G14 -> 57200 | J14: =松山紹介_補綴価格表!F16*B14 -> 349600 | K14: =J14/G14 -> 0.76398601
A15: 前歯 ジルコニアセラミック S級 6本（上顎前歯フル） | B15: 6 | C15: =松山紹介_補綴価格表!B16 -> 143000 | D15: =B15*C15 -> 858000 | E15: =IF(B15<=5,0.1,IF(B15<=9,0.15,0.2)) -> 0.15 | F15: =ROUND(C15*(1-E15),0)*B15 -> 729300 | G15: =松山紹介_補綴価格表!D16*B15 -> 686400 | H15: =D15-G15 -> 171600 | I15: =F15-G15 -> 42900 | J15: =松山紹介_補綴価格表!F16*B15 -> 524400 | K15: =J15/G15 -> 0.76398601
A16: 前歯 スーパーエナメル 6本 | B16: 6 | C16: =松山紹介_補綴価格表!B19 -> 99000 | D16: =B16*C16 -> 594000 | E16: =IF(B16<=5,0.1,IF(B16<=9,0.15,0.2)) -> 0.15 | F16: =ROUND(C16*(1-E16),0)*B16 -> 504900 | G16: =松山紹介_補綴価格表!D19*B16 -> 475200 | H16: =D16-G16 -> 118800 | I16: =F16-G16 -> 29700 | J16: =松山紹介_補綴価格表!F19*B16 -> 313200 | K16: =J16/G16 -> 0.65909091
A17: 前歯 ラミネートベニア 6本 | B17: 6 | C17: =松山紹介_補綴価格表!B18 -> 110000 | D17: =B17*C17 -> 660000 | E17: =IF(B17<=5,0.1,IF(B17<=9,0.15,0.2)) -> 0.15 | F17: =ROUND(C17*(1-E17),0)*B17 -> 561000 | G17: =松山紹介_補綴価格表!D18*B17 -> 528000 | H17: =D17-G17 -> 132000 | I17: =F17-G17 -> 33000 | J17: =松山紹介_補綴価格表!F18*B17 -> 432000 | K17: =J17/G17 -> 0.81818182
A18: 前歯 ジルコニアセラミック ノーマル 12本（上下） | B18: 12 | C18: =松山紹介_補綴価格表!B17 -> 110000 | D18: =B18*C18 -> 1320000 | E18: =IF(B18<=5,0.1,IF(B18<=9,0.15,0.2)) -> 0.2 | F18: =ROUND(C18*(1-E18),0)*B18 -> 1056000 | G18: =松山紹介_補綴価格表!D17*B18 -> 1056000 | H18: =D18-G18 -> 264000 | I18: =F18-G18 -> 0 | J18: =松山紹介_補綴価格表!F17*B18 -> 828000 | K18: =J18/G18 -> 0.78409091
A20: ■ 矯正（インビザライン）｜松山紹介＝①矯正治療費は据え置き、②矯正検査診断料 44,000円のみ無料
A21: 矯正 インビザラインフル｜コンプリ オプション2 1件 | B21: 1 | C21: =松山紹介_矯正価格表!G12 -> 924000 | D21: =B21*C21 -> 924000 | E21: 0 | F21: =D21 -> 924000 | G21: =松山紹介_矯正価格表!H12*B21 -> 880000 | H21: =D21-G21 -> 44000 | I21: =F21-G21 -> 44000 | J21: =松山紹介_矯正価格表!K12*B21 -> 670800 | K21: =J21/G21 -> 0.76227273
A22: 矯正 インビザラインモデレート（26枚）両顎 1件 | B22: 1 | C22: =松山紹介_矯正価格表!G13 -> 591800 | D22: =B22*C22 -> 591800 | E22: 0 | F22: =D22 -> 591800 | G22: =松山紹介_矯正価格表!H13*B22 -> 547800 | H22: =D22-G22 -> 44000 | I22: =F22-G22 -> 44000 | J22: =松山紹介_矯正価格表!K13*B22 -> 377600 | K22: =J22/G22 -> 0.68930267
A23: 矯正 インビザラインライト（14枚）両顎 1件 | B23: 1 | C23: =松山紹介_矯正価格表!G15 -> 481800 | D23: =B23*C23 -> 481800 | E23: 0 | F23: =D23 -> 481800 | G23: =松山紹介_矯正価格表!H15*B23 -> 437800 | H23: =D23-G23 -> 44000 | I23: =F23-G23 -> 44000 | J23: =松山紹介_矯正価格表!K15*B23 -> 294120 | K23: =J23/G23 -> 0.67181361
A24: 矯正 小児一期｜ファースト オプション2 1件 | B24: 1 | C24: =松山紹介_矯正価格表!G21 -> 594000 | D24: =B24*C24 -> 594000 | E24: 0 | F24: =D24 -> 594000 | G24: =松山紹介_矯正価格表!H21*B24 -> 550000 | H24: =D24-G24 -> 44000 | I24: =F24-G24 -> 44000 | J24: =松山紹介_矯正価格表!K21*B24 -> 387600 | K24: =J24/G24 -> 0.70472727
A25: 矯正 小児二期治療（フェーズ2） 1件 | B25: 1 | C25: =松山紹介_矯正価格表!G24 -> 484000 | D25: =B25*C25 -> 484000 | E25: 0 | F25: =D25 -> 484000 | G25: =松山紹介_矯正価格表!H24*B25 -> 440000 | H25: =D25-G25 -> 44000 | I25: =F25-G25 -> 44000 | J25: =松山紹介_矯正価格表!K24*B25 -> 281500 | K25: =J25/G25 -> 0.63977273
A27: この表でいちばん大事な列＝I列「医院の実質負担」
A28: ◆ H列（患者メリット）は患者さんから見た『お得額』。I列（医院の実質負担）は医院が新たに失う額で、この2つは一致しない。
A29: ◆ 紹介がなくても本数に応じた割引は出していたので、10本以上のケースでは通常割引が既に20%＝松山紹介にしても医院の負担はゼロ円。
A30: ◆ 逆に1〜2本の少数症例では、通常10%→紹介20%となり定価の10%分が実質負担になる。負担が出るのは小さい症例のほうという構造。
A31: ◆ 矯正の治療費は据え置きなので値引きゼロ。実質負担＝別建て請求の検査診断料44,000円（本来もらえたはずの分）が1件ごとに発生する。
A34: 【損益分岐】月に何件の紹介が来たら、従来の月額紹介料と同じコストになるか
A35: 想定ケース | B35: 1件あたりの 医院の実質負担 | C35: 月額 30,000円 の場合 | D35: 月額 50,000円 の場合 | E35: 月額 80,000円 の場合 | F35: 月額 100,000円 の場合 | G35: 月額 150,000円 の場合 | H35: 上のD6に入れた 実額の場合
A36: 臼歯 フルジルコニアクラウン 1本 | B36: =I11 -> 9900 | C36: =IF($B36=0,"負担ゼロ",ROUND(30000/$B36,1)) -> 3 | D36: =IF($B36=0,"負担ゼロ",ROUND(50000/$B36,1)) -> 5.1 | E36: =IF($B36=0,"負担ゼロ",ROUND(80000/$B36,1)) -> 8.1 | F36: =IF($B36=0,"負担ゼロ",ROUND(100000/$B36,1)) -> 10.1 | G36: =IF($B36=0,"負担ゼロ",ROUND(150000/$B36,1)) -> 15.2 | H36: =IF($B36=0,"負担ゼロ",ROUND($D$6/$B36,1)) -> 5.1
A37: 臼歯 フルジルコニアクラウン 3本 | B37: =I12 -> 29700 | C37: =IF($B37=0,"負担ゼロ",ROUND(30000/$B37,1)) -> 1 | D37: =IF($B37=0,"負担ゼロ",ROUND(50000/$B37,1)) -> 1.7 | E37: =IF($B37=0,"負担ゼロ",ROUND(80000/$B37,1)) -> 2.7 | F37: =IF($B37=0,"負担ゼロ",ROUND(100000/$B37,1)) -> 3.4 | G37: =IF($B37=0,"負担ゼロ",ROUND(150000/$B37,1)) -> 5.1 | H37: =IF($B37=0,"負担ゼロ",ROUND($D$6/$B37,1)) -> 1.7
A38: 前歯 ジルコニアセラミック S級 6本（上顎前歯フル） | B38: =I15 -> 42900 | C38: =IF($B38=0,"負担ゼロ",ROUND(30000/$B38,1)) -> 0.7 | D38: =IF($B38=0,"負担ゼロ",ROUND(50000/$B38,1)) -> 1.2 | E38: =IF($B38=0,"負担ゼロ",ROUND(80000/$B38,1)) -> 1.9 | F38: =IF($B38=0,"負担ゼロ",ROUND(100000/$B38,1)) -> 2.3 | G38: =IF($B38=0,"負担ゼロ",ROUND(150000/$B38,1)) -> 3.5 | H38: =IF($B38=0,"負担ゼロ",ROUND($D$6/$B38,1)) -> 1.2
A39: 前歯 ジルコニアセラミック ノーマル 12本（上下） | B39: =I18 -> 0 | C39: =IF($B39=0,"負担ゼロ",ROUND(30000/$B39,1)) -> 負担ゼロ | D39: =IF($B39=0,"負担ゼロ",ROUND(50000/$B39,1)) -> 負担ゼロ | E39: =IF($B39=0,"負担ゼロ",ROUND(80000/$B39,1)) -> 負担ゼロ | F39: =IF($B39=0,"負担ゼロ",ROUND(100000/$B39,1)) -> 負担ゼロ | G39: =IF($B39=0,"負担ゼロ",ROUND(150000/$B39,1)) -> 負担ゼロ | H39: =IF($B39=0,"負担ゼロ",ROUND($D$6/$B39,1)) -> 負担ゼロ
A40: 矯正 インビザラインモデレート（26枚）両顎 1件 | B40: =I22 -> 44000 | C40: =IF($B40=0,"負担ゼロ",ROUND(30000/$B40,1)) -> 0.7 | D40: =IF($B40=0,"負担ゼロ",ROUND(50000/$B40,1)) -> 1.1 | E40: =IF($B40=0,"負担ゼロ",ROUND(80000/$B40,1)) -> 1.8 | F40: =IF($B40=0,"負担ゼロ",ROUND(100000/$B40,1)) -> 2.3 | G40: =IF($B40=0,"負担ゼロ",ROUND(150000/$B40,1)) -> 3.4 | H40: =IF($B40=0,"負担ゼロ",ROUND($D$6/$B40,1)) -> 1.1
A41: ※ 数値は「月◯件までなら、従来の月額紹介料より安く済む」という件数。これを超えた月は従来より支出が増えるが、その分だけ売上も増えている点に注意。
A43: 従来方式と新方式のちがい（構造）
A44: ◆ 従来（月額固定）：紹介がゼロの月も満額を支払う。年間で D7 セルの金額が確定支出になる。相手の実績と支払いが連動しない。
A45: ◆ 新方式（来院時の値引き）：来院がなければ負担ゼロ。負担が出るのは必ず売上が立ったときだけで、しかも上表のとおり粗利率65%以上は必ず残る。
A46: ◆ そのかわり、紹介が想定以上に集中すると値引き総額が青天井になりうる。運用ルールのシートで月間上限・有効期限を必ず決めておくこと。

Sheet 運用ルール・確認事項
A1: 松山翼様ご紹介プラン｜運用ルールと確認事項
A2: 配布用の価格表（松山翼様にお渡しする版）とセットで運用してください。以下は医院側の取り決めです。
A4: 1. 適用条件（価格表にも明記する）
A5: ◆ 対象＝松山翼様からのご紹介であれば誰でも。暁の城の在籍者に限定しない（院長決裁事項）。初診の受付時に「松山翼さんの紹介」と申告があった方。
A6: ◆ 【重要】対象を「松山翼様の紹介」とする以上、店舗の在籍者に限定した場合より範囲は広い。紹介の連鎖も起こりうるため、月間上限と有効期限を必ずセットで決める。
A7: ◆ 【重要】自費診療のみが対象。保険診療の一部負担金は法令上、値引き・免除ができないため必ず対象外とする。
A8: ◆ 他の割引・キャンペーン・モニター価格との併用は不可。本数によるまとめ割引とも併用しない（20%OFFが上限で、それ以上は重ねない）。
A9: ◆ 補綴20%OFFは当院の値引き下限。「もう少し」と言われても、これ以上は下げられない旨を最初に伝えておく。
A11: 2. 価格の中身
A12: ◆ 補綴（セラミック治療）：全品目 一律20%OFF。1本から適用、本数の条件なし。
A13: ◆ 矯正（インビザライン）：請求は【①矯正治療費】と【②矯正検査診断料 44,000円】の別建て。①は定価据え置きのまま、②のみを無料にする。
A14: ◆ 矯正のパッケージ価格を下げないのは、粗利率が64〜76%と低く値引きの余地がないため。検査診断料は原価ゼロなので、同じ「お得感」を医院の持ち出しゼロで出せる。
... A41: ◆ 従来松山翼様にお支払いしていた月額紹介料の実額も未共有のため、損益分岐シミュレーションでは仮に50,000円で計算しています（D6セルを実額に書き換えてください）。
